README.md
setup.cfg
setup.py
star_scan/__init__.py
star_scan/scanner.py
star_scan.egg-info/PKG-INFO
star_scan.egg-info/SOURCES.txt
star_scan.egg-info/dependency_links.txt
star_scan.egg-info/top_level.txt