Metadata-Version: 2.1
Name: star-scan
Version: 0.8
Summary: Simple port scanning module
Home-page: https://github.com/starhound/star_scan
Author: Wesley Reid
Author-email: wesleyreid0@gmail.com
License: MIT
Download-URL: https://github.com/starhound/star_scan/archive/main.zip
Keywords: NETWORK,UTILITY,PORT SCANNER
Platform: UNKNOWN
Classifier: Development Status :: 3 - Alpha
Classifier: Intended Audience :: Developers
Classifier: Topic :: Software Development :: Build Tools
Classifier: License :: OSI Approved :: MIT License
Classifier: Programming Language :: Python :: 3.8
Classifier: Programming Language :: Python :: 3.9
